ghtrending/__init__.py
ghtrending/__main__.py
ghtrending/__version__.py
ghtrending/ghtrending.py
ghtrending-0.2.2.dist-info/LICENSE
ghtrending-0.2.2.dist-info/METADATA
ghtrending-0.2.2.dist-info/NOTICE
ghtrending-0.2.2.dist-info/WHEEL
ghtrending-0.2.2.dist-info/entry_points.txt
ghtrending-0.2.2.dist-info/top_level.txt
ghtrending-0.2.2.dist-info/RECORD
