Metadata-Version: 2.1
Name: ghtrending
Version: 0.2.2
Summary: Github Trending Explorer
Home-page: https://github.com/chinsyo/ghtrending
Author: chinsyo
Author-email: chinsyo@sina.cn
License: MIT
Platform: UNKNOWN
Requires-Dist: lxml
Requires-Dist: requests
